src/__init__.py
src/cli.py
src/conf.py
src/logging.py
src/common/__init__.py
src/common/_version.py
src/common/pass_through_list.py
src/common/plugin.py
src/common/run_command.py
src/common/validate_allowed_workspace.py
tfremote-0.0.36.dist-info/LICENSE
tfremote-0.0.36.dist-info/METADATA
tfremote-0.0.36.dist-info/WHEEL
tfremote-0.0.36.dist-info/entry_points.txt
tfremote-0.0.36.dist-info/top_level.txt
tfremote-0.0.36.dist-info/RECORD
