Metadata-Version: 2.1
Name: tfremote
Version: 0.0.36
Summary: Terraform wrapper to manage state across multiple cloud providers
Home-page: https://github.com/tomarv2/tfremote
Author: Varun Tomar
Author-email: varuntomar2019@gmail.com
License: Apache Software License
Platform: UNKNOWN
Classifier: Programming Language :: Python :: 3.6
Classifier: Operating System :: OS Independent
Requires-Python: >=3.6
Requires-Dist: pyhcl
Requires-Dist: regex
Requires-Dist: ruamel.yaml
